fintonic_ocr_handler
