Metadata-Version: 2.1
Name: fintonic-ocr-handler
Version: 0.6
Summary: Librería para procesar errores del ocr
Home-page: https://www.fintonic.mx/
Author: fintonic
Author-email: raulperez@fintonic.com
License: MIT
Keywords: fintonic,error,handler,extraction,ocr
Platform: UNKNOWN
Classifier: Development Status :: 3 - Alpha
Classifier: Intended Audience :: Developers
Classifier: Topic :: Software Development :: Build Tools
Classifier: License :: OSI Approved :: MIT License
Classifier: Programming Language :: Python :: 3.5
Classifier: Programming Language :: Python :: 3.6
Classifier: Programming Language :: Python :: 3.7
Classifier: Programming Language :: Python :: 3.8
Classifier: Programming Language :: Python :: 3.9
License-File: LICENSE.txt
